python_utils/__init__.py
python_utils/asyncio_utils.py
python_utils/generic_utils.py
python_utils/read_env.py
python_utils/static_class.py
python_utils/time_utils.py
python_utils/trace_prints.py
python_utils/ttl_cache.py
samsteady_python_utils-1.0.22.dist-info/METADATA
samsteady_python_utils-1.0.22.dist-info/WHEEL
samsteady_python_utils-1.0.22.dist-info/top_level.txt
samsteady_python_utils-1.0.22.dist-info/RECORD
